{
  "sprint": "calib-cure-b2",
  "features": [
    {
      "id": "F001",
      "title": "Spike 闸门·解算原型 + 真实数据验准配方（通用PnP+异面点+精修，go/no-go 报告）",
      "priority": "high",
      "executor": "generator",
      "status": "completed",
      "depends": [],
      "acceptance": "`scripts/spike/calib_solve/`（严格隔离，纯 numpy，**不 import main.py、不改任何产品代码**，同 calib-cure-b1 spike 隔离范式 spec §D5）：(1) 候选解算器原型——通用 PnP 接受**异面点** z∈{0,2700,竖直边}（非共面单应）+ 非线性精修（全点最小化总重投影）+ 点位条件数/退化度量；(2) 真实数据台——读 `apps/api/tests/fixtures/prod_calibrations.json`（11 条真实生产点击）+ 只读拉取生产病例照片副本（`deploysvr:.../uploads/D/empty/{472015c4…,ed881ccf…}.jpg`，**PIPL 绝不入 git**）；(3) 多高度标注小工具（在照片上人工点选地面+天花板/竖直点，补足现生产数据只有地面点的空白）；(4) 对比量化候选 vs 现（solve_pnp/calibrate）：reproj（稳健+最大）、相机高度∈[800,2200]/离房距离、**线框叠真实照片目检贴合**、诚实门下失败率，覆盖 ≥3 房型×≥2 机位。**产出报告** `docs/test-reports/calib-cure-b2-spike-YYYYMMDD.md`：go/no-go + 验准配方（异面点取哪些/需几个、精修方法、退化阈值、reproj 稳健指标与门值）+ no-go/部分时的降级建议。**注：本条为研究码非产品，报告非产品 signoff；产品件独立性由 F008 L2 保证。**",
      "notes": "spike 是本批闸门：Planner 据 F001 报告裁决配方（pre-impl-adjudication）后才 lock F002–F007 acceptance。若 no-go，F002+ 范围就地重议。真值/噪声/真实几何的方向性数值实验主上下文已跑（见 spec §1），F001 用**真实点击**把配方钉死。"
    },
    {
      "id": "F002",
      "title": "异面特征点供给（derive_features 增天花板角/门窗顶/竖直墙棱，破共面退化）",
      "priority": "high",
      "executor": "generator",
      "status": "pending",
      "depends": [
        "F001"
      ],
      "acceptance": "**acceptance 以 F001 spike 验准配方为准（Planner 裁决后 lock）。** 方向（spec §D1）：扩 `calib_features.derive_features`(calib_features.py:38) 在现地面点（墙角+门/落地窗地面交点）外新增**异面点**——墙-天花板角(z=`perspective._REAL_CEILING_MM`=2700，**严禁借 axon 1450**)、门/窗竖框顶点、墙角竖直棱(z=0..2700)；kind 扩展 ceiling_corner/door_head/window_head/wall_edge_vertical；id 稳定可复算、排序确定性。层高/门窗高数据来源在 F001 已确认（无字段则用常量并注明）。**pytest 同 commit**：新 kind 派生数量/坐标断言、既有 derive_features 单测零回归（test_calib_features）。",
      "notes": "现只派生 z=0（calib_features.py:52-120）。异面点是让通用 PnP 良态的关键供给。"
    },
    {
      "id": "F003",
      "title": "通用 PnP + 非线性精修（solve_pnp 升级为接受异面点 + 全点精修降噪）",
      "priority": "high",
      "executor": "generator",
      "status": "pending",
      "depends": [
        "F001",
        "F002"
      ],
      "acceptance": "**acceptance 以 F001 配方为准。** 方向（spec §D2）：`calib_features.solve_pnp`(calib_features.py:168) 从共面单应分解升级为**接受异面点的通用 PnP**（DLT 投影矩阵分解 / EPnP 思路 + 焦距扫描；纯 numpy、确定性、左手系 det(R)=-1 与既有一致）；解后加**非线性精修**（全点对最小化总重投影，把点击噪声平均掉）。**数学内核既有单测必须仍绿**：`test_perspective` 合成真值往返 <2px、`test_calib_features`；生产 11 条 lines 重放（test_prod_fixture_*）行为按 F001 裁决处理（若精修致数值变化，同 commit 更新基线并注明理由）。**pytest 同 commit**：异面点合成真值往返 <2px、含噪输入 reproj 较现显著下降（用 spec §1 噪声台钉阈值）。",
      "notes": "现共面路径 _homography(137)/_pose_candidates(152)。通用 PnP 后共面输入仍需可解（退化到现路径或统一新路径）。"
    },
    {
      "id": "F004",
      "title": "退化/可见性守门 + 可行动引导（解算前拦近共线/太少/单一高度，杜绝静默垃圾相机）",
      "priority": "high",
      "executor": "generator",
      "status": "pending",
      "depends": [
        "F001",
        "F003"
      ],
      "acceptance": "**acceptance 以 F001 配方为准（阈值由 spike 定）。** 方向（spec §D3）：解算前（端点/校验层 main.py，**不改数学内核**）查点位条件数——近共线/像素太挤/全在单一高度/有效点<N → 返回明确中文可行动提示（『再点一个天花板角』『点到对面墙把点铺开』），杜绝现 solve_pnp 对共线点静默给灾难相机的行为。**pytest 同 commit**：退化点集被拦（附提示文案）、良态点集放行、既有校验（_validate_points_payload main.py:944 / _validate_calibration_payload:867）零回归。",
      "notes": "共线比/条件数度量在 F001 spike 已试算（主上下文实验用奇异值比 s[-1]/s[0]，r_study≈0 即死局）。"
    },
    {
      "id": "F005",
      "title": "稳健 reproj 指标 + 门保持诚实（max→RMS/分位，单坏点不误杀，400/409家族零回归）",
      "priority": "high",
      "executor": "generator",
      "status": "pending",
      "depends": [
        "F001",
        "F003"
      ],
      "acceptance": "**acceptance 以 F001 配方为准（指标选型/门值由 spike 定）。** 方向（spec §D4）：`assess_calibration_quality`(perspective.py:612) 现 reproj=所有点最大值(perspective.py:637)，换**稳健指标**（RMS 或 P75/P90 + 单点离群另标）。**门仍诚实**（线框贴合仍是真判据，不放水；非放宽门）。既有 400/409 家族（STALE/DEGENERATE_GUIDE/BAD_CALIBRATION，main.py:2759-2790 + 保存 400）**零回归**：同 code 同 HTTP 语义；`CALIB_MAX_REPROJ_PX` escape hatch 保留。**pytest 同 commit**：稳健指标下单坏点不判死、真歪相机仍判 bad、既有门测试零回归。",
      "notes": "门语义不变是本批红线（用户裁决：门是对的）。此条只改指标形状不改门的诚实性。"
    },
    {
      "id": "F006",
      "title": "前端多高度点选（地面+天花板/竖直点点选 + 点位铺开引导，复用设计系统）",
      "priority": "high",
      "executor": "generator",
      "status": "pending",
      "depends": [
        "F001",
        "F002",
        "F003"
      ],
      "acceptance": "**acceptance 以 F001 配方为准。** 方向（spec §D6）：`FeaturePointCalibrator.tsx` 支持**地面+天花板/竖直点**点选（平面小窗高亮当前目标 + 高度提示），呼应 F004 守门做点位铺开引导；预览确认门语义不变（复用 F002/b1 的 CalibrationPreview + quality.ok）。**复用设计系统组件**（Modal/Badge/Button/NoticeBanner/LoadingState，见既有 import [[grandtianfu-reuse-design-system]]）；成对 `dark:`；禁 `bg-*-50` 硬编码。tsc + yarn lint 绿。",
      "notes": "现 FeaturePointCalibrator 只点地面点（onPickPoint→px→world 来自 features）。多高度需 features 带 z（F002 供给）+ UI 标高度。"
    },
    {
      "id": "F007",
      "title": "专家（线+角）模式降级为高级选项 + 明确警告（数学最脆 σ=3px→55%）",
      "priority": "medium",
      "executor": "generator",
      "status": "pending",
      "depends": [
        "F001",
        "F006"
      ],
      "acceptance": "**acceptance 以 F001 配方为准（去留由 spike 结论定）。** 方向（spec §D5）：`PerspectiveCalibrator.tsx`(模式路由:93) 把专家（线+角）模式降级为高级选项 + 明确警告（『手画线法对精度极敏感，建议用特征点模式』），或按 spike 结论决定去留；**不删既有 F002 两步提交逻辑**（保留可回退）。tsc + yarn lint 绿；D6 规范。",
      "notes": "专家模式 σ=3px→55% 撞门（spec §1），最脆。默认已是 features 模式（PerspectiveCalibrator.tsx:93）。"
    },
    {
      "id": "F008",
      "title": "L2 验收·真实浏览器重标生产病例 + 落位改善 + 稳健性报告（独立 evaluator）",
      "priority": "high",
      "executor": "evaluator",
      "status": "pending",
      "depends": [
        "F002",
        "F003",
        "F004",
        "F005",
        "F006",
        "F007"
      ],
      "acceptance": "隔离 evaluator 对**产品代码**独立验收（无自评铁则）：(1) 两套 pytest 全绿 0 skip（合成真值往返<2px、异面点新单测、生产重放按裁决基线、既有 400/409 家族零回归）；golden 逐字节不动；ruff 本批代码 clean；(2) tsc+yarn lint 绿；前端 D6 规范逐条查；(3) **[L2] 真实浏览器**：以新流程重标生产病例照片（798/f4d + 常见房型各一）→ **线框贴合目检 + 保存成功 + 出图落位改善**，对比 b1 前失败率给定量/半定量结论；(4) 铁律 10 commit tag 映射；(5) **诚实边界写进 signoff**：哪些房型/机位仍救不动，是否需后续构图引导/EXIF 焦距立项。报告落 `docs/test-reports/`。",
      "notes": "L2 需用户授权真实浏览器操作 + 只读拉取病例照片（PIPL 不入 git）。这是判定'解算真的修好了没有'的唯一实物门。"
    }
  ]
}